nv_one_logger/no_init.md
nv_one_logger/wandb/exporter/__init__.py
nv_one_logger/wandb/exporter/wandb_exporter.py
nv_one_logger/wandb/no_init.md
nv_one_logger_wandb-2.3.0.dist-info/LICENSE
nv_one_logger_wandb-2.3.0.dist-info/METADATA
nv_one_logger_wandb-2.3.0.dist-info/WHEEL
nv_one_logger_wandb-2.3.0.dist-info/RECORD
