Metadata-Version: 2.1
Name: nv-one-logger-wandb
Version: 2.3.0
Summary: Extensions to onelogger library to use Weights and Biases as a backend.
License: Apache-2.0
Author: HWInf-MLWFO
Author-email: HWInf-MLWFO-E2E-Dev@exchange.nvidia.com
Requires-Python: >=3.9,<4.0
Classifier: License :: OSI Approved :: Apache Software License
Classifier: Programming Language :: Python :: 3
Classifier: Programming Language :: Python :: 3.9
Classifier: Programming Language :: Python :: 3.10
Classifier: Programming Language :: Python :: 3.11
Classifier: Programming Language :: Python :: 3.12
Classifier: Programming Language :: Python :: 3.13
Requires-Dist: StrEnum (>=0.4.0,<0.5.0)
Requires-Dist: nv-one-logger-core (>=2.3.0,<3.0.0)
Requires-Dist: typing-extensions (>=4.12.2,<5.0.0)
Requires-Dist: urllib3 (>=2.5.0)
Requires-Dist: wandb (>=0.20.1,<0.21.0)
